opengeodemand/__init__.py
opengeodemand/analysis.py
opengeodemand/core.py
opengeodemand/districts.py
opengeodemand/optimization.py
opengeodemand/osm.py
opengeodemand/profiles.py
opengeodemand/simulation.py
opengeodemand/utils.py
opengeodemand/data/india_district_ec_hces.geojson
opengeodemand-0.2.1.dist-info/METADATA
opengeodemand-0.2.1.dist-info/WHEEL
opengeodemand-0.2.1.dist-info/top_level.txt
opengeodemand-0.2.1.dist-info/RECORD
