Metadata-Version: 2.1
Name: opengeodemand
Version: 0.2.1
Summary: Open Source Geospatial Demand Simulation Engine
Author: Dipit & Usman
Requires-Python: >=3.8
Requires-Dist: geopandas >=0.10
Requires-Dist: pandas >=1.3
Requires-Dist: numpy
Requires-Dist: shapely
Requires-Dist: osmnx >=1.9
Requires-Dist: scikit-learn
Requires-Dist: seaborn
Requires-Dist: matplotlib
Requires-Dist: folium
Requires-Dist: mapclassify
Requires-Dist: requests
Requires-Dist: pyogrio
